{
  "timestamp": "2024-09-30T03:07:04.127Z",
  "reports": [
    {
      "url": "https://www.mazipan.space/",
      "device": "mobile",
      "perf": 0.72,
      "fid": 0,
      "lcp": 2413.02,
      "cls": 0.00431,
      "fcp": 2413.02,
      "fci": 0,
      "tbt": 1015.71,
      "tti": 5687.15,
      "si": 2413.02,
      "req": 36,
      "size": 436895
    },
    {
      "url": "https://www.mazipan.space/",
      "device": "desktop",
      "perf": 0.99,
      "fid": 0,
      "lcp": 718.26,
      "cls": 0.00281,
      "fcp": 678.26,
      "fci": 0,
      "tbt": 55,
      "tti": 1371.4,
      "si": 915.42,
      "req": 38,
      "size": 516992
    }
  ]
}